Metadata-Version: 2.1
Name: ssi-forest
Version: 0.1.1
Summary: Semi-supervised isolation forest
Home-page: https://github.com/hombit/ssi-forest
Author: Konstantin Malanchev
Author-email: hombit@gmail.com
License: MIT
Platform: UNKNOWN
Classifier: Intended Audience :: Science/Research
Classifier: License :: OSI Approved :: MIT License
Classifier: Programming Language :: Python :: 3
Requires-Python: >=3.7
License-File: LICENSE
